pip_uall/__init__.py
pip_uall/__main__.py
pip_uall/pip_uall.py
pip_uall-0.0.4.dist-info/LICENSE
pip_uall-0.0.4.dist-info/METADATA
pip_uall-0.0.4.dist-info/WHEEL
pip_uall-0.0.4.dist-info/entry_points.txt
pip_uall-0.0.4.dist-info/top_level.txt
pip_uall-0.0.4.dist-info/RECORD
