Metadata-Version: 2.1
Name: pip-uall
Version: 0.0.4
Summary: A tool to update pip packages
Home-page: https://github,com/ClasherKasten/pip_ualls
Author: ClasherKasten
Author-email: cfb1470@gmail.com
License: UNKNOWN
Project-URL: Bug Tracker, https://github.com/ClasherKasten/pip_uall/issues
Platform: UNKNOWN
Classifier: Programming Language :: Python :: 3
Classifier: License :: OSI Approved :: MIT License
Classifier: Operating System :: OS Independent
License-File: LICENSE
